CHANGES.rst
CONTRIBUTORS.rst
MANIFEST.in
README.rst
setup.cfg
setup.py
collective/__init__.py
collective.relationfieldwidget.egg-info/PKG-INFO
collective.relationfieldwidget.egg-info/SOURCES.txt
collective.relationfieldwidget.egg-info/dependency_links.txt
collective.relationfieldwidget.egg-info/entry_points.txt
collective.relationfieldwidget.egg-info/namespace_packages.txt
collective.relationfieldwidget.egg-info/not-zip-safe
collective.relationfieldwidget.egg-info/requires.txt
collective.relationfieldwidget.egg-info/top_level.txt
collective/relationfieldwidget/__init__.py
collective/relationfieldwidget/configure.zcml
collective/relationfieldwidget/interfaces.py
collective/relationfieldwidget/overrides.zcml
collective/relationfieldwidget/setuphandlers.py
collective/relationfieldwidget/testing.py
collective/relationfieldwidget/browser/__init__.py
collective/relationfieldwidget/browser/configure.zcml
collective/relationfieldwidget/browser/widget.py
collective/relationfieldwidget/browser/widget.py~
collective/relationfieldwidget/browser/widget_related_items.pt
collective/relationfieldwidget/locales/collective.relationfieldwidget.pot
collective/relationfieldwidget/locales/update.sh
collective/relationfieldwidget/profiles/default/browserlayer.xml
collective/relationfieldwidget/profiles/default/collectiverelationfieldwidget_default.txt
collective/relationfieldwidget/profiles/default/metadata.xml
collective/relationfieldwidget/profiles/uninstall/browserlayer.xml
collective/relationfieldwidget/profiles/uninstall/collectiverelationfieldwidget_uninstall.txt
collective/relationfieldwidget/tests/__init__.py
collective/relationfieldwidget/tests/test_robot.py
collective/relationfieldwidget/tests/test_setup.py
collective/relationfieldwidget/tests/robot/test_example.robot
docs/LICENSE.GPL
docs/LICENSE.rst
docs/index.rst