Metadata-Version: 1.1
Name: collective.relationfieldwidget
Version: 1.0a1
Summary: RelationField Widget for Plone 5
Home-page: https://pypi.python.org/pypi/collective.relationfieldwidget
Author: Matt Grant
Author-email: matt.grant@foodstuffs-si.co.nz
License: GPL
Keywords: Python Plone
Platform: UNKNOWN
Classifier: Environment :: Web Environment
Classifier: Framework :: Plone
Classifier: Framework :: Plone :: 5.0
Classifier: Programming Language :: Python
Classifier: Programming Language :: Python :: 2.7
Classifier: Operating System :: OS Independent
Classifier: License :: OSI Approved :: GNU General Public License v2 (GPLv2)
